MMLToolbox/MML.py
MMLToolbox/__init__.py
MMLToolbox/arduino/ArduinoHandler.py
MMLToolbox/arduino/__init__.py
MMLToolbox/coord/CoordSystem.py
MMLToolbox/coord/WASDHandler.py
MMLToolbox/coord/__init__.py
MMLToolbox/localMag/MagneticAligner.py
MMLToolbox/localMag/MagneticCalibration.py
MMLToolbox/localMag/MagneticCalibration_V1.py
MMLToolbox/localMag/OpticAligner.py
MMLToolbox/localMag/StoreMagneticAligner.py
MMLToolbox/localMag/__init__.py
MMLToolbox/ni/NISystem.py
MMLToolbox/ni/__init__.py
MMLToolbox/optic/OpticSystem.py
MMLToolbox/optic/__init__.py
MMLToolbox/pxi/EvalPostProc.py
MMLToolbox/pxi/ILController.py
MMLToolbox/pxi/ILController_Epstein_AG.py
MMLToolbox/pxi/ILController_RSST.py
MMLToolbox/pxi/ILController_RSST_AG.py
MMLToolbox/pxi/ILController_RSST_AG_old.py
MMLToolbox/pxi/MatModel.py
MMLToolbox/pxi/MatModel_AG.py
MMLToolbox/pxi/OptSignalForm.py
MMLToolbox/pxi/PXIControl.py
MMLToolbox/pxi/PXIHandler.py
MMLToolbox/pxi/PXIPostProcessing.py
MMLToolbox/pxi/PXIPreProcessing.py
MMLToolbox/pxi/SignalHandler.py
MMLToolbox/pxi/StoreSetup.py
MMLToolbox/pxi/__init__.py
MMLToolbox/pxi/epstein_main_controller_JA_ILC_final.py
MMLToolbox/senis/SenisSystem.py
MMLToolbox/senis/__init__.py
MMLToolbox/util/LogHandler.py
MMLToolbox/util/StoreH5.py
MMLToolbox/util/__init__.py
MMLToolbox/util/h5Handler.py
MMLToolbox/util/types.py
MMLToolbox/util/util.py
mmltoolbox-1.8.13.dist-info/licenses/LICENSE
mmltoolbox-1.8.13.dist-info/METADATA
mmltoolbox-1.8.13.dist-info/WHEEL
mmltoolbox-1.8.13.dist-info/top_level.txt
mmltoolbox-1.8.13.dist-info/RECORD
