Metadata-Version: 2.4
Name: MMLToolbox
Version: 1.8.13
Home-page: https://www.tugraz.at/institute/igte/home/
Author: Andreas Gschwentner<andreas.gschwentner@tugraz.at>, Elias Alizadeh Saboor<alizadehsaboor@tugraz.at>
Keywords: data acquisition,measurements
Classifier: Development Status :: 4 - Beta
Classifier: Intended Audience :: Science/Research
Classifier: Topic :: Scientific/Engineering
Classifier: License :: OSI Approved :: MIT License
Classifier: Programming Language :: Python :: 3.9
License-File: LICENSE
Requires-Dist: numpy
Requires-Dist: nidmm
Requires-Dist: nidaqmx
Requires-Dist: niswitch
Requires-Dist: h5py
Requires-Dist: scipy
Requires-Dist: matplotlib
Requires-Dist: serial
Requires-Dist: pandas
Dynamic: author
Dynamic: classifier
Dynamic: description
Dynamic: description-content-type
Dynamic: home-page
Dynamic: keywords
Dynamic: license-file
Dynamic: requires-dist
